{"id":"5c07fcf5-203a-45d3-8882-f5ae45c49eb5","revision":0,"last_node_id":30,"last_link_id":64,"nodes":[{"id":7,"type":"CLIPTextEncode","pos":[690,840],"size":[425.27801513671875,180.6060791015625],"flags":{},"order":6,"mode":0,"inputs":[{"localized_name":"clip","name":"clip","type":"CLIP","link":5},{"localized_name":"text","name":"text","type":"STRING","widget":{"name":"text"},"link":null}],"outputs":[{"localized_name":"CONDITIONING","name":"CONDITIONING","type":"CONDITIONING","slot_index":0,"links":[6]}],"properties":{"cnr_id":"comfy-core","ver":"0.3.50","Node name for S&R":"CLIPTextEncode"},"widgets_values":["blurry, noisy, messy, lowres, jpeg, artifacts, ill, distorted, malformed"]},{"id":8,"type":"VAEDecode","pos":[1615,586],"size":[140,46],"flags":{},"order":11,"mode":0,"inputs":[{"localized_name":"samples","name":"samples","type":"LATENT","link":7},{"localized_name":"vae","name":"vae","type":"VAE","link":8}],"outputs":[{"localized_name":"IMAGE","name":"IMAGE","type":"IMAGE","slot_index":0,"links":[51]}],"properties":{"cnr_id":"comfy-core","ver":"0.3.50","Node name for S&R":"VAEDecode"},"widgets_values":[]},{"id":4,"type":"CheckpointLoaderSimple","pos":[-675,575],"size":[550,200],"flags":{},"order":0,"mode":0,"inputs":[{"localized_name":"ckpt_name","name":"ckpt_name","type":"COMBO","widget":{"name":"ckpt_name"},"link":null}],"outputs":[{"localized_name":"MODEL","name":"MODEL","type":"MODEL","slot_index":0,"links":[48]},{"localized_name":"CLIP","name":"CLIP","type":"CLIP","slot_index":1,"links":[3,5]},{"localized_name":"VAE","name":"VAE","type":"VAE","slot_index":2,"links":[8]}],"properties":{"cnr_id":"comfy-core","ver":"0.3.50","Node name for S&R":"CheckpointLoaderSimple"},"widgets_values":["turbovisionxlSuperFastXLBasedOnNew_tvxlV431Bakedvae.safetensors"]},{"id":5,"type":"EmptyLatentImage","pos":[801,1097],"size":[315,106],"flags":{},"order":1,"mode":0,"inputs":[{"localized_name":"width","name":"width","type":"INT","widget":{"name":"width"},"link":null},{"localized_name":"height","name":"height","type":"INT","widget":{"name":"height"},"link":null},{"localized_name":"batch_size","name":"batch_size","type":"INT","widget":{"name":"batch_size"},"link":null}],"outputs":[{"localized_name":"LATENT","name":"LATENT","type":"LATENT","slot_index":0,"links":[2]}],"properties":{"cnr_id":"comfy-core","ver":"0.3.50","Node name for S&R":"EmptyLatentImage"},"widgets_values":[1024,1024,4]},{"id":3,"type":"KSampler","pos":[1247,586],"size":[315,262],"flags":{},"order":10,"mode":0,"inputs":[{"localized_name":"model","name":"model","type":"MODEL","link":56},{"localized_name":"positive","name":"positive","type":"CONDITIONING","link":4},{"localized_name":"negative","name":"negative","type":"CONDITIONING","link":6},{"localized_name":"latent_image","name":"latent_image","type":"LATENT","link":2},{"localized_name":"seed","name":"seed","type":"INT","widget":{"name":"seed"},"link":null},{"localized_name":"steps","name":"steps","type":"INT","widget":{"name":"steps"},"link":null},{"localized_name":"cfg","name":"cfg","type":"FLOAT","widget":{"name":"cfg"},"link":null},{"localized_name":"sampler_name","name":"sampler_name","type":"COMBO","widget":{"name":"sampler_name"},"link":null},{"localized_name":"scheduler","name":"scheduler","type":"COMBO","widget":{"name":"scheduler"},"link":null},{"localized_name":"denoise","name":"denoise","type":"FLOAT","widget":{"name":"denoise"},"link":null}],"outputs":[{"localized_name":"LATENT","name":"LATENT","type":"LATENT","slot_index":0,"links":[7]}],"properties":{"cnr_id":"comfy-core","ver":"0.3.50","Node name for S&R":"KSampler"},"widgets_values":[51776022780006,"fixed",8,1.8,"dpmpp_2m","karras",1]},{"id":25,"type":"IPAdapterUnifiedLoader","pos":[25,375],"size":[315,78],"flags":{},"order":4,"mode":0,"inputs":[{"localized_name":"model","name":"model","type":"MODEL","link":48},{"localized_name":"ipadapter","name":"ipadapter","shape":7,"type":"IPADAPTER","link":null},{"localized_name":"preset","name":"preset","type":"COMBO","widget":{"name":"preset"},"link":null}],"outputs":[{"localized_name":"model","name":"model","type":"MODEL","slot_index":0,"links":[57]},{"localized_name":"ipadapter","name":"ipadapter","type":"IPADAPTER","slot_index":1,"links":[54]}],"properties":{"cnr_id":"comfyui_ipadapter_plus","ver":"a0f451a5113cf9becb0847b92884cb10cbdec0ef","Node name for S&R":"IPAdapterUnifiedLoader"},"widgets_values":["PLUS (high strength)"]},{"id":29,"type":"PrepImageForClipVision","pos":[150,-25],"size":[315,106],"flags":{},"order":8,"mode":0,"inputs":[{"localized_name":"image","name":"image","type":"IMAGE","link":59},{"localized_name":"interpolation","name":"interpolation","type":"COMBO","widget":{"name":"interpolation"},"link":null},{"localized_name":"crop_position","name":"crop_position","type":"COMBO","widget":{"name":"crop_position"},"link":null},{"localized_name":"sharpening","name":"sharpening","type":"FLOAT","widget":{"name":"sharpening"},"link":null}],"outputs":[{"localized_name":"IMAGE","name":"IMAGE","type":"IMAGE","slot_index":0,"links":[64]}],"properties":{"cnr_id":"comfyui_ipadapter_plus","ver":"a0f451a5113cf9becb0847b92884cb10cbdec0ef","Node name for S&R":"PrepImageForClipVision"},"widgets_values":["LANCZOS","top",0.05]},{"id":30,"type":"PrepImageForClipVision","pos":[150,-400],"size":[315,106],"flags":{},"order":7,"mode":0,"inputs":[{"localized_name":"image","name":"image","type":"IMAGE","link":61},{"localized_name":"interpolation","name":"interpolation","type":"COMBO","widget":{"name":"interpolation"},"link":null},{"localized_name":"crop_position","name":"crop_position","type":"COMBO","widget":{"name":"crop_position"},"link":null},{"localized_name":"sharpening","name":"sharpening","type":"FLOAT","widget":{"name":"sharpening"},"link":null}],"outputs":[{"localized_name":"IMAGE","name":"IMAGE","type":"IMAGE","slot_index":0,"links":[63]}],"properties":{"cnr_id":"comfyui_ipadapter_plus","ver":"a0f451a5113cf9becb0847b92884cb10cbdec0ef","Node name for S&R":"PrepImageForClipVision"},"widgets_values":["LANCZOS","top",0.05]},{"id":6,"type":"CLIPTextEncode","pos":[690,610],"size":[422.84503173828125,164.31304931640625],"flags":{},"order":5,"mode":0,"inputs":[{"localized_name":"clip","name":"clip","type":"CLIP","link":3},{"localized_name":"text","name":"text","type":"STRING","widget":{"name":"text"},"link":null}],"outputs":[{"localized_name":"CONDITIONING","name":"CONDITIONING","type":"CONDITIONING","slot_index":0,"links":[4]}],"properties":{"cnr_id":"comfy-core","ver":"0.3.50","Node name for S&R":"CLIPTextEncode"},"widgets_values":["Mona Lisa"]},{"id":27,"type":"IPAdapterStyleComposition","pos":[675,225],"size":[428.4000244140625,322],"flags":{},"order":9,"mode":0,"inputs":[{"localized_name":"model","name":"model","type":"MODEL","link":57},{"localized_name":"ipadapter","name":"ipadapter","type":"IPADAPTER","link":54},{"localized_name":"image_style","name":"image_style","type":"IMAGE","link":63},{"localized_name":"image_composition","name":"image_composition","type":"IMAGE","link":64},{"localized_name":"image_negative","name":"image_negative","shape":7,"type":"IMAGE","link":null},{"localized_name":"attn_mask","name":"attn_mask","shape":7,"type":"MASK","link":null},{"localized_name":"clip_vision","name":"clip_vision","shape":7,"type":"CLIP_VISION","link":null},{"localized_name":"weight_style","name":"weight_style","type":"FLOAT","widget":{"name":"weight_style"},"link":null},{"localized_name":"weight_composition","name":"weight_composition","type":"FLOAT","widget":{"name":"weight_composition"},"link":null},{"localized_name":"expand_style","name":"expand_style","type":"BOOLEAN","widget":{"name":"expand_style"},"link":null},{"localized_name":"combine_embeds","name":"combine_embeds","type":"COMBO","widget":{"name":"combine_embeds"},"link":null},{"localized_name":"start_at","name":"start_at","type":"FLOAT","widget":{"name":"start_at"},"link":null},{"localized_name":"end_at","name":"end_at","type":"FLOAT","widget":{"name":"end_at"},"link":null},{"localized_name":"embeds_scaling","name":"embeds_scaling","type":"COMBO","widget":{"name":"embeds_scaling"},"link":null}],"outputs":[{"localized_name":"MODEL","name":"MODEL","type":"MODEL","slot_index":0,"links":[56]}],"properties":{"cnr_id":"comfyui_ipadapter_plus","ver":"a0f451a5113cf9becb0847b92884cb10cbdec0ef","Node name for S&R":"IPAdapterStyleComposition"},"widgets_values":[0.8,2,true,"average",0,1,"V only"]},{"id":26,"type":"PreviewImage","pos":[1950,575],"size":[1000,975],"flags":{},"order":12,"mode":0,"inputs":[{"localized_name":"images","name":"images","type":"IMAGE","link":51}],"outputs":[],"properties":{"cnr_id":"comfy-core","ver":"0.3.50","Node name for S&R":"PreviewImage"},"widgets_values":[]},{"id":28,"type":"LoadImage","pos":[-300,-25],"size":[315,314],"flags":{},"order":3,"mode":0,"inputs":[{"localized_name":"image","name":"image","type":"COMBO","widget":{"name":"image"},"link":null},{"localized_name":"choose file to upload","name":"upload","type":"IMAGEUPLOAD","widget":{"name":"upload"},"link":null}],"outputs":[{"localized_name":"IMAGE","name":"IMAGE","type":"IMAGE","slot_index":0,"links":[59]},{"localized_name":"MASK","name":"MASK","type":"MASK","links":null}],"properties":{"cnr_id":"comfy-core","ver":"0.3.50","Node name for S&R":"LoadImage"},"widgets_values":["ComfyUI_00043_.png","image"]},{"id":12,"type":"LoadImage","pos":[-425,-425],"size":[315,314],"flags":{},"order":2,"mode":0,"inputs":[{"localized_name":"image","name":"image","type":"COMBO","widget":{"name":"image"},"link":null},{"localized_name":"choose file to upload","name":"upload","type":"IMAGEUPLOAD","widget":{"name":"upload"},"link":null}],"outputs":[{"localized_name":"IMAGE","name":"IMAGE","type":"IMAGE","slot_index":0,"links":[61]},{"localized_name":"MASK","name":"MASK","type":"MASK","links":null}],"properties":{"cnr_id":"comfy-core","ver":"0.3.50","Node name for S&R":"LoadImage"},"widgets_values":["ComfyUI_00034_.png","image"]}],"links":[[2,5,0,3,3,"LATENT"],[3,4,1,6,0,"CLIP"],[4,6,0,3,1,"CONDITIONING"],[5,4,1,7,0,"CLIP"],[6,7,0,3,2,"CONDITIONING"],[7,3,0,8,0,"LATENT"],[8,4,2,8,1,"VAE"],[48,4,0,25,0,"MODEL"],[51,8,0,26,0,"IMAGE"],[54,25,1,27,1,"IPADAPTER"],[56,27,0,3,0,"MODEL"],[57,25,0,27,0,"MODEL"],[59,28,0,29,0,"IMAGE"],[61,12,0,30,0,"IMAGE"],[63,30,0,27,2,"IMAGE"],[64,29,0,27,3,"IMAGE"]],"groups":[],"config":{},"extra":{"ds":{"scale":0.8441365377694208,"offset":[799.7722391165773,652.4640296826174]}},"version":0.4}